[
  {
    "name": "18Comic",
    "file": "18Comic.png"
  },
  {
    "name": "930mh",
    "file": "930mh.png"
  },
  {
    "name": "9yao old",
    "file": "9yao_old.png"
  },
  {
    "name": "9yao older",
    "file": "9yao_older.png"
  },
  {
    "name": "9yao sjzxsp",
    "file": "9yao_sjzxsp.png"
  },
  {
    "name": "AdobeStockWM",
    "file": "AdobeStockWM.png"
  },
  {
    "name": "Adulti02(1)",
    "file": "Adulti02(1).png"
  },
  {
    "name": "AgitWM W1080",
    "file": "AgitWM_W1080.png"
  },
  {
    "name": "BiliBiliWM W1259H1800",
    "file": "BiliBiliWM_W1259H1800.png"
  },
  {
    "name": "Bilibili 2480x3508",
    "file": "Bilibili 2480x3508 .png"
  },
  {
    "name": "BilibiliWM ChainsawMan W2000",
    "file": "BilibiliWM_ChainsawMan_W2000.png"
  },
  {
    "name": "Bilibili 1909x3000",
    "file": "Bilibili_1909x3000.png"
  },
  {
    "name": "BlueBetCasino",
    "file": "BlueBetCasino.png"
  },
  {
    "name": "Buzztoon 2",
    "file": "Buzztoon 2.png"
  },
  {
    "name": "Buzztoon",
    "file": "Buzztoon.png"
  },
  {
    "name": "ClipartofWM",
    "file": "ClipartofWM.png"
  },
  {
    "name": "Colamanhua",
    "file": "Colamanhua.png"
  },
  {
    "name": "DL Raw Co",
    "file": "DL-Raw_Co.png"
  },
  {
    "name": "DL raw",
    "file": "DL-raw.png"
  },
  {
    "name": "DMZJ 2",
    "file": "DMZJ 2.png"
  },
  {
    "name": "DMZJ",
    "file": "DMZJ.png"
  },
  {
    "name": "EmotesCreatorWM",
    "file": "EmotesCreatorWM.png"
  },
  {
    "name": "ExtractedSearchWatermarkWidth719",
    "file": "ExtractedSearchWatermarkWidth719.png"
  },
  {
    "name": "ExtractedSpowikiBottomWM W600H3004",
    "file": "ExtractedSpowikiBottomWM_W600H3004.png"
  },
  {
    "name": "ExtractedSpowikiTopWatermark600V2",
    "file": "ExtractedSpowikiTopWatermark600V2.png"
  },
  {
    "name": "Freestory new with text",
    "file": "Freestory new with text.png"
  },
  {
    "name": "Freestory02 older",
    "file": "Freestory02 older.png"
  },
  {
    "name": "GoogleWM2 W720",
    "file": "GoogleWM2_W720.png"
  },
  {
    "name": "Hodu Walnut",
    "file": "Hodu Walnut.png"
  },
  {
    "name": "IStockWM1",
    "file": "IStockWM1.png"
  },
  {
    "name": "IStockWM2",
    "file": "IStockWM2.png"
  },
  {
    "name": "Jijiman",
    "file": "Jijiman.png"
  },
  {
    "name": "Kuaikanmanhua 2023",
    "file": "Kuaikanmanhua_2023.png"
  },
  {
    "name": "Manga1001 (1)",
    "file": "Manga1001 (1).png"
  },
  {
    "name": "Manga1001(2)",
    "file": "Manga1001(2).png"
  },
  {
    "name": "ManhuaDao",
    "file": "ManhuaDao.png"
  },
  {
    "name": "Manhwas men",
    "file": "Manhwas.men.png"
  },
  {
    "name": "Manhwasmen",
    "file": "Manhwasmen.png"
  },
  {
    "name": "Miritoon",
    "file": "Miritoon.png"
  },
  {
    "name": "Newtoki Coloured",
    "file": "Newtoki Coloured.png"
  },
  {
    "name": "Newtoki Greyscale High opacity (1)",
    "file": "Newtoki Greyscale High opacity (1).png"
  },
  {
    "name": "Newtoki Greyscale Low opacity",
    "file": "Newtoki Greyscale Low opacity.png"
  },
  {
    "name": "NewtokiWM2",
    "file": "NewtokiWM2.png"
  },
  {
    "name": "SPTWatermark",
    "file": "SPTWatermark.png"
  },
  {
    "name": "SearchBar",
    "file": "SearchBar.png"
  },
  {
    "name": "Sharktoon",
    "file": "Sharktoon.png"
  },
  {
    "name": "Shonen Jump (1)",
    "file": "Shonen Jump (1).png"
  },
  {
    "name": "Shonen Jump",
    "file": "Shonen Jump.png"
  },
  {
    "name": "ShutterstockSmallWM",
    "file": "ShutterstockSmallWM.png"
  },
  {
    "name": "SkymangaBottomLeftWM W720H2500 V2",
    "file": "SkymangaBottomLeftWM_W720H2500_V2.png"
  },
  {
    "name": "SkymangaTopRightWM W720H2500",
    "file": "SkymangaTopRightWM_W720H2500.png"
  },
  {
    "name": "Spowiki netWM",
    "file": "Spowiki.netWM.png"
  },
  {
    "name": "Spowiki",
    "file": "Spowiki.png"
  },
  {
    "name": "Spowiki2023 600",
    "file": "Spowiki2023_600.png"
  },
  {
    "name": "Spowiki2023 719",
    "file": "Spowiki2023_719.png"
  },
  {
    "name": "SpowikiCasinoWM",
    "file": "SpowikiCasinoWM.png"
  },
  {
    "name": "Taomanhua",
    "file": "Taomanhua.png"
  },
  {
    "name": "Tencent 1800px",
    "file": "Tencent_1800px.png"
  },
  {
    "name": "Toomics",
    "file": "Toomics.png"
  },
  {
    "name": "Toptoon",
    "file": "Toptoon.png"
  },
  {
    "name": "TwitterDaum (complete)",
    "file": "TwitterDaum (complete).png"
  },
  {
    "name": "TwitterDaum",
    "file": "TwitterDaum.png"
  },
  {
    "name": "U17",
    "file": "U17.png"
  },
  {
    "name": "Yaddal",
    "file": "Yaddal.png"
  },
  {
    "name": "YaddalTv",
    "file": "YaddalTv.png"
  },
  {
    "name": "Zhiyin Manke Bigger",
    "file": "Zhiyin Manke Bigger.png"
  },
  {
    "name": "Zhiyin Manke",
    "file": "Zhiyin Manke.png"
  },
  {
    "name": "adulti02",
    "file": "adulti02.png"
  },
  {
    "name": "ak2vod",
    "file": "ak2vod.png"
  },
  {
    "name": "all",
    "file": "all.png"
  },
  {
    "name": "allspo1",
    "file": "allspo1.png"
  },
  {
    "name": "avsnoop",
    "file": "avsnoop.png"
  },
  {
    "name": "azoremanga",
    "file": "azoremanga.png"
  },
  {
    "name": "bakamh",
    "file": "bakamh.png"
  },
  {
    "name": "baozimh 2",
    "file": "baozimh 2.png"
  },
  {
    "name": "baozimh variant",
    "file": "baozimh variant.png"
  },
  {
    "name": "baozimh",
    "file": "baozimh.png"
  },
  {
    "name": "bilibili variant",
    "file": "bilibili variant.png"
  },
  {
    "name": "bilibili",
    "file": "bilibili.png"
  },
  {
    "name": "bilibili 2000x2920",
    "file": "bilibili_2000x2920.png"
  },
  {
    "name": "bluebet 720",
    "file": "bluebet_720.png"
  },
  {
    "name": "bunnygirl",
    "file": "bunnygirl.png"
  },
  {
    "name": "duri3 hodu small text",
    "file": "duri3 hodu small text.png"
  },
  {
    "name": "duri3 small text",
    "file": "duri3 small text.png"
  },
  {
    "name": "duri3",
    "file": "duri3.png"
  },
  {
    "name": "extracted",
    "file": "extracted.png"
  },
  {
    "name": "fairman messed up",
    "file": "fairman messed up.png"
  },
  {
    "name": "fairman138",
    "file": "fairman138.png"
  },
  {
    "name": "freestory precursor",
    "file": "freestory precursor.png"
  },
  {
    "name": "gross gradient big",
    "file": "gross gradient big.png"
  },
  {
    "name": "guoman8",
    "file": "guoman8.png"
  },
  {
    "name": "h2 (spowiki) 600",
    "file": "h2 (spowiki) 600.png"
  },
  {
    "name": "h2 (spowiki) 719",
    "file": "h2 (spowiki) 719.png"
  },
  {
    "name": "hodu excessive",
    "file": "hodu excessive.png"
  },
  {
    "name": "hodu large",
    "file": "hodu large.png"
  },
  {
    "name": "hodu small",
    "file": "hodu small.png"
  },
  {
    "name": "hodu",
    "file": "hodu.png"
  },
  {
    "name": "ikanmh",
    "file": "ikanmh.png"
  },
  {
    "name": "kuaikan 2020 1280px",
    "file": "kuaikan 2020_1280px.png"
  },
  {
    "name": "kuaikan 2020 1080x",
    "file": "kuaikan_2020_1080x.png"
  },
  {
    "name": "kuaikan 2021 1280x",
    "file": "kuaikan_2021_1280x.png"
  },
  {
    "name": "kuaikan dark 1080x",
    "file": "kuaikan_dark_1080x.png"
  },
  {
    "name": "kuaikan dark 1280x",
    "file": "kuaikan_dark_1280x.png"
  },
  {
    "name": "kuaikan dark 750x",
    "file": "kuaikan_dark_750x.png"
  },
  {
    "name": "kuaikan old 1080x",
    "file": "kuaikan_old_1080x.png"
  },
  {
    "name": "kuaikan old 1280x v2",
    "file": "kuaikan_old_1280x_v2.png"
  },
  {
    "name": "kuaikan old 750x",
    "file": "kuaikan_old_750x.png"
  },
  {
    "name": "kuaikanmanhua 1280px",
    "file": "kuaikanmanhua 1280px.png"
  },
  {
    "name": "kuaikanmanhua 750x",
    "file": "kuaikanmanhua 750x.png"
  },
  {
    "name": "kuaikanmanhua1080x",
    "file": "kuaikanmanhua1080x.png"
  },
  {
    "name": "kuaikanmanhua 2023 1280px",
    "file": "kuaikanmanhua_2023-1280px.png"
  },
  {
    "name": "kuaikanmanhua 2023 1440px",
    "file": "kuaikanmanhua_2023-1440px.png"
  },
  {
    "name": "manhuasfacg",
    "file": "manhuasfacg.png"
  },
  {
    "name": "manman",
    "file": "manman.png"
  },
  {
    "name": "mt ssul1 opaque",
    "file": "mt-ssul1 opaque.png"
  },
  {
    "name": "mtoo google",
    "file": "mtoo google.png"
  },
  {
    "name": "newtoki (made in abyss, lighter)",
    "file": "newtoki (made in abyss, lighter).png"
  },
  {
    "name": "newtoki (made in abyss, more opaque)",
    "file": "newtoki (made in abyss, more opaque).png"
  },
  {
    "name": "newtoki 42",
    "file": "newtoki 42.png"
  },
  {
    "name": "novelagit 646 A",
    "file": "novelagit_646_A.png"
  },
  {
    "name": "novelagit 646 B",
    "file": "novelagit_646_B.png"
  },
  {
    "name": "novelagit 690 A",
    "file": "novelagit_690_A.png"
  },
  {
    "name": "novelagit 690 B",
    "file": "novelagit_690_B.png"
  },
  {
    "name": "novelagit 760",
    "file": "novelagit_760.png"
  },
  {
    "name": "oncapan 1",
    "file": "oncapan 1.png"
  },
  {
    "name": "oncapan liei",
    "file": "oncapan liei.png"
  },
  {
    "name": "qumanku small",
    "file": "qumanku_small.png"
  },
  {
    "name": "qumanku w1080",
    "file": "qumanku_w1080.png"
  },
  {
    "name": "something  in",
    "file": "something -in.png"
  },
  {
    "name": "spowiki even older (with bg)",
    "file": "spowiki even older (with bg).png"
  },
  {
    "name": "spowiki even older (with stroke)",
    "file": "spowiki even older (with stroke).png"
  },
  {
    "name": "spowiki even older",
    "file": "spowiki even older.png"
  },
  {
    "name": "spowiki 720",
    "file": "spowiki_720.png"
  },
  {
    "name": "spowiki old 740",
    "file": "spowiki_old_740.png"
  },
  {
    "name": "tencent 1280",
    "file": "tencent 1280.png"
  },
  {
    "name": "tencent 1500",
    "file": "tencent 1500.png"
  },
  {
    "name": "tencent 1600",
    "file": "tencent 1600.png"
  },
  {
    "name": "tencent 750",
    "file": "tencent 750.png"
  },
  {
    "name": "tencent 800",
    "file": "tencent 800.png"
  },
  {
    "name": "tencent 1600px",
    "file": "tencent_1600px.png"
  },
  {
    "name": "tencent old",
    "file": "tencent_old.png"
  },
  {
    "name": "tkr085",
    "file": "tkr085.png"
  },
  {
    "name": "tkr095",
    "file": "tkr095.png"
  },
  {
    "name": "tkr098",
    "file": "tkr098.png"
  },
  {
    "name": "tkr103",
    "file": "tkr103.png"
  },
  {
    "name": "tkr108",
    "file": "tkr108.png"
  },
  {
    "name": "tkr111",
    "file": "tkr111.png"
  },
  {
    "name": "tkr126",
    "file": "tkr126.png"
  },
  {
    "name": "todaytoon",
    "file": "todaytoon.png"
  },
  {
    "name": "toonkor",
    "file": "toonkor.png"
  },
  {
    "name": "toonkor129",
    "file": "toonkor129.png"
  },
  {
    "name": "tt28",
    "file": "tt28.png"
  },
  {
    "name": "upnaver",
    "file": "upnaver.png"
  },
  {
    "name": "veryoldspowiki Search Bar",
    "file": "veryoldspowiki Search Bar.png"
  },
  {
    "name": "wb as 4410 3",
    "file": "wb-as_4410 3.png"
  },
  {
    "name": "wb as 4410 1",
    "file": "wb-as_4410_1.png"
  },
  {
    "name": "wb as 4410 2",
    "file": "wb-as_4410_2.png"
  },
  {
    "name": "weibo2020",
    "file": "weibo2020.png"
  },
  {
    "name": "whitebetcasino600",
    "file": "whitebetcasino600.png"
  },
  {
    "name": "whitebetcasino720",
    "file": "whitebetcasino720.png"
  },
  {
    "name": "wm",
    "file": "wm.jpg"
  },
  {
    "name": "wn oy 4410 1",
    "file": "wn-oy_4410 1.png"
  },
  {
    "name": "wn oy 4410 1",
    "file": "wn-oy_4410_1.png"
  },
  {
    "name": "yaddal small text",
    "file": "yaddal small text.png"
  },
  {
    "name": "yy28",
    "file": "yy28.png"
  }
]